google_purchase/__init__.py
google_purchase/google_purchase.py
google_purchase/responses.py
pyinapp_purchase-0.0.5.dist-info/LICENSE
pyinapp_purchase-0.0.5.dist-info/METADATA
pyinapp_purchase-0.0.5.dist-info/WHEEL
pyinapp_purchase-0.0.5.dist-info/top_level.txt
pyinapp_purchase-0.0.5.dist-info/RECORD
