Metadata-Version: 2.1
Name: pyinapp-purchase
Version: 0.0.5
Summary: pyinapp_purchase is an open-source Python library designed to simplify and securely validate in-app purchase tokens server side.
Home-page: https://github.com/Michael-Jalloh/pyinapp_purchase
Author: Michael Jalloh
Author-email: michaeljalloh19@gmail.com
License: MIT
Project-URL: issues, https://github.com/Michael-Jalloh/pyinapp_purchase/issues
Project-URL: source, https://github.com/Michael-Jalloh/pyinapp_purchase
Keywords: inapp purchase,inapp,purchase,google inapp purchase
Platform: any
Classifier: Development Status :: 3 - Alpha
Classifier: Intended Audience :: Developers
Classifier: Topic :: Software Development :: Build Tools
Classifier: License :: OSI Approved :: MIT License
Classifier: Programming Language :: Python :: 3.7
Classifier: Programming Language :: Python :: 3.8
Classifier: Programming Language :: Python :: 3.9
Classifier: Programming Language :: Python :: 3.10
Classifier: Programming Language :: Python :: 3.11
Classifier: Programming Language :: Python :: 3.12
Classifier: Programming Language :: Python :: 3.13
License-File: LICENSE
Requires-Dist: PyJWT
Requires-Dist: requests
Requires-Dist: cryptography
